{
  "en": {
    "SiteMetadata.titleDefault": "HUMPBUCK Montres - Meaningful Gifts of Time and Love",
    "SiteMetadata.descriptionDefault": "Handcrafted timepieces designed to stay by your side and witness life's meaningful moments.",
    "SiteMetadata.ogTitle": "HUMPBUCK Montres - Meaningful Gifts of Time and Love",
    "SiteMetadata.ogDescription": "Handcrafted timepieces designed to stay by your side and witness life's meaningful moments.",
    "Footer.tagline": "Handcrafted timepieces designed to stay by your side and witness life's meaningful moments.",
    "Home.metaTitle": "HUMPBUCK Montres - Meaningful Gifts of Time and Love",
    "Home.metaDescription": "Handcrafted timepieces designed to stay by your side and witness life's meaningful moments.",
    "Home.ogTitle": "HUMPBUCK Montres - Meaningful Gifts of Time and Love",
    "Home.ogDescription": "Handcrafted timepieces designed to stay by your side and witness life's meaningful moments.",
    "Home.mechanicalHeroTitle": "HUMPBUCK Montres",
    "Home.mechanicalHeroLead": "Handcrafted timepieces designed to stay by your side and witness life's meaningful moments.",
    "Home.mechanicalHeroBadge": "Gifts · Time & Love",
    "Home.mechanicalHeroChipAutomatic": "Craftsmanship",
    "Home.mechanicalHeroChipSkeleton": "Milestones",
    "Home.mechanicalHeroChipFinishing": "Companionship",
    "Home.newsletterBody": "Handcrafted timepieces designed to stay by your side and witness life's meaningful moments.",
    "Shop.metaTitle": "Shop meaningful gift watches",
    "Shop.metaDescription": "Handcrafted timepieces designed to stay by your side and witness life's meaningful moments.",
    "Shop.ogTitle": "Shop meaningful gift watches · HUMPBUCK",
    "Shop.ogDescription": "Handcrafted timepieces designed to stay by your side and witness life's meaningful moments.",
    "Shop.title": "Handcrafted timepieces designed to stay by your side and witness life's meaningful moments.",
    "AboutPage.metaTitle": "About — HUMPBUCK Montres",
    "AboutPage.metaDescription": "Handcrafted timepieces designed to stay by your side and witness life's meaningful moments.",
    "BlogPage.metaDescription": "Handcrafted timepieces designed to stay by your side and witness life's meaningful moments.",
    "BlogPage.intro": "Handcrafted timepieces designed to stay by your side and witness life's meaningful moments.",
    "Home.recommendedIntro": "Handcrafted timepieces designed to stay by your side and witness life's meaningful moments.",
    "Home.newsletterTitle": "NEW WATCHES DROPS",
    "BlogPage.metaTitle": "Blog — HUMPBUCK",
    "BlogPage.ogTitle": "Blog — HUMPBUCK",
    "BlogPage.kicker": "Journal",
    "BlogPage.title": "Blog"
  },
  "de": {
    "SiteMetadata.titleDefault": "HUMPBUCK Uhren – Bedeutungsvolle Geschenke aus Zeit und Liebe",
    "SiteMetadata.descriptionDefault": "Handgefertigte Zeitmesser, die an Ihrer Seite bleiben und die bedeutungsvollen Momente des Lebens miterleben.",
    "SiteMetadata.ogTitle": "HUMPBUCK Uhren – Bedeutungsvolle Geschenke aus Zeit und Liebe",
    "SiteMetadata.ogDescription": "Handgefertigte Zeitmesser, die an Ihrer Seite bleiben und die bedeutungsvollen Momente des Lebens miterleben.",
    "Footer.tagline": "Handgefertigte Zeitmesser, die an Ihrer Seite bleiben und die bedeutungsvollen Momente des Lebens miterleben.",
    "Home.metaTitle": "HUMPBUCK Uhren – Bedeutungsvolle Geschenke aus Zeit und Liebe",
    "Home.metaDescription": "Handgefertigte Zeitmesser, die an Ihrer Seite bleiben und die bedeutungsvollen Momente des Lebens miterleben.",
    "Home.ogTitle": "HUMPBUCK Uhren – Bedeutungsvolle Geschenke aus Zeit und Liebe",
    "Home.ogDescription": "Handgefertigte Zeitmesser, die an Ihrer Seite bleiben und die bedeutungsvollen Momente des Lebens miterleben.",
    "Home.mechanicalHeroTitle": "HUMPBUCK Uhren",
    "Home.mechanicalHeroLead": "Handgefertigte Zeitmesser, die an Ihrer Seite bleiben und die bedeutungsvollen Momente des Lebens miterleben.",
    "Home.mechanicalHeroBadge": "Geschenke · Zeit & Liebe",
    "Home.mechanicalHeroChipAutomatic": "Handwerkskunst",
    "Home.mechanicalHeroChipSkeleton": "Meilensteine",
    "Home.mechanicalHeroChipFinishing": "Begleitung",
    "Home.newsletterBody": "Handgefertigte Zeitmesser, die an Ihrer Seite bleiben und die bedeutungsvollen Momente des Lebens miterleben.",
    "Shop.metaTitle": "Bedeutungsvolle Geschenk-Uhren shoppen",
    "Shop.metaDescription": "Handgefertigte Zeitmesser, die an Ihrer Seite bleiben und die bedeutungsvollen Momente des Lebens miterleben.",
    "Shop.ogTitle": "Bedeutungsvolle Geschenk-Uhren shoppen · HUMPBUCK",
    "Shop.ogDescription": "Handgefertigte Zeitmesser, die an Ihrer Seite bleiben und die bedeutungsvollen Momente des Lebens miterleben.",
    "Shop.title": "Handgefertigte Zeitmesser, die an Ihrer Seite bleiben und die bedeutungsvollen Momente des Lebens miterleben.",
    "AboutPage.metaTitle": "Über uns — HUMPBUCK Uhren",
    "AboutPage.metaDescription": "Handgefertigte Zeitmesser, die an Ihrer Seite bleiben und die bedeutungsvollen Momente des Lebens miterleben.",
    "BlogPage.metaDescription": "Handgefertigte Zeitmesser, die an Ihrer Seite bleiben und die bedeutungsvollen Momente des Lebens miterleben.",
    "BlogPage.intro": "Handgefertigte Zeitmesser, die an Ihrer Seite bleiben und die bedeutungsvollen Momente des Lebens miterleben.",
    "Home.recommendedIntro": "Handgefertigte Zeitmesser, die an Ihrer Seite bleiben und die bedeutungsvollen Momente des Lebens miterleben.",
    "Home.newsletterTitle": "NEUE UHR-RELEASES",
    "BlogPage.metaTitle": "Blog — HUMPBUCK",
    "BlogPage.ogTitle": "Blog — HUMPBUCK",
    "BlogPage.kicker": "Journal",
    "BlogPage.title": "Blog"
  },
  "es": {
    "SiteMetadata.titleDefault": "HUMPBUCK Montres - Regalos con significado de tiempo y amor",
    "SiteMetadata.descriptionDefault": "Piezas artesanales diseñadas para acompañarte y presenciar los momentos significativos de la vida.",
    "SiteMetadata.ogTitle": "HUMPBUCK Montres - Regalos con significado de tiempo y amor",
    "SiteMetadata.ogDescription": "Piezas artesanales diseñadas para acompañarte y presenciar los momentos significativos de la vida.",
    "Footer.tagline": "Piezas artesanales diseñadas para acompañarte y presenciar los momentos significativos de la vida.",
    "Home.metaTitle": "HUMPBUCK Montres - Regalos con significado de tiempo y amor",
    "Home.metaDescription": "Piezas artesanales diseñadas para acompañarte y presenciar los momentos significativos de la vida.",
    "Home.ogTitle": "HUMPBUCK Montres - Regalos con significado de tiempo y amor",
    "Home.ogDescription": "Piezas artesanales diseñadas para acompañarte y presenciar los momentos significativos de la vida.",
    "Home.mechanicalHeroTitle": "HUMPBUCK Montres",
    "Home.mechanicalHeroLead": "Piezas artesanales diseñadas para acompañarte y presenciar los momentos significativos de la vida.",
    "Home.mechanicalHeroBadge": "Regalos · Tiempo y amor",
    "Home.mechanicalHeroChipAutomatic": "Artesanía",
    "Home.mechanicalHeroChipSkeleton": "Hitos",
    "Home.mechanicalHeroChipFinishing": "Compañía",
    "Home.newsletterBody": "Piezas artesanales diseñadas para acompañarte y presenciar los momentos significativos de la vida.",
    "Shop.metaTitle": "Comprar relojes regalo con significado",
    "Shop.metaDescription": "Piezas artesanales diseñadas para acompañarte y presenciar los momentos significativos de la vida.",
    "Shop.ogTitle": "Comprar relojes regalo con significado · HUMPBUCK",
    "Shop.ogDescription": "Piezas artesanales diseñadas para acompañarte y presenciar los momentos significativos de la vida.",
    "Shop.title": "Piezas artesanales diseñadas para acompañarte y presenciar los momentos significativos de la vida.",
    "AboutPage.metaTitle": "Sobre nosotros — HUMPBUCK Montres",
    "AboutPage.metaDescription": "Piezas artesanales diseñadas para acompañarte y presenciar los momentos significativos de la vida.",
    "BlogPage.metaDescription": "Piezas artesanales diseñadas para acompañarte y presenciar los momentos significativos de la vida.",
    "BlogPage.intro": "Piezas artesanales diseñadas para acompañarte y presenciar los momentos significativos de la vida.",
    "Home.recommendedIntro": "Piezas artesanales diseñadas para acompañarte y presenciar los momentos significativos de la vida.",
    "Home.newsletterTitle": "NUEVOS LANZAMIENTOS DE RELOJES",
    "BlogPage.metaTitle": "Blog — HUMPBUCK",
    "BlogPage.ogTitle": "Blog — HUMPBUCK",
    "BlogPage.kicker": "Diario",
    "BlogPage.title": "Blog"
  },
  "pt": {
    "SiteMetadata.titleDefault": "HUMPBUCK Montres - Presentes significativos de tempo e amor",
    "SiteMetadata.descriptionDefault": "Peças artesanais feitas para estar ao seu lado e testemunhar os momentos significativos da vida.",
    "SiteMetadata.ogTitle": "HUMPBUCK Montres - Presentes significativos de tempo e amor",
    "SiteMetadata.ogDescription": "Peças artesanais feitas para estar ao seu lado e testemunhar os momentos significativos da vida.",
    "Footer.tagline": "Peças artesanais feitas para estar ao seu lado e testemunhar os momentos significativos da vida.",
    "Home.metaTitle": "HUMPBUCK Montres - Presentes significativos de tempo e amor",
    "Home.metaDescription": "Peças artesanais feitas para estar ao seu lado e testemunhar os momentos significativos da vida.",
    "Home.ogTitle": "HUMPBUCK Montres - Presentes significativos de tempo e amor",
    "Home.ogDescription": "Peças artesanais feitas para estar ao seu lado e testemunhar os momentos significativos da vida.",
    "Home.mechanicalHeroTitle": "HUMPBUCK Montres",
    "Home.mechanicalHeroLead": "Peças artesanais feitas para estar ao seu lado e testemunhar os momentos significativos da vida.",
    "Home.mechanicalHeroBadge": "Presentes · Tempo e amor",
    "Home.mechanicalHeroChipAutomatic": "Artesanato",
    "Home.mechanicalHeroChipSkeleton": "Marcos",
    "Home.mechanicalHeroChipFinishing": "Companhia",
    "Home.newsletterBody": "Peças artesanais feitas para estar ao seu lado e testemunhar os momentos significativos da vida.",
    "Shop.metaTitle": "Comprar relógios presente com significado",
    "Shop.metaDescription": "Peças artesanais feitas para estar ao seu lado e testemunhar os momentos significativos da vida.",
    "Shop.ogTitle": "Comprar relógios presente com significado · HUMPBUCK",
    "Shop.ogDescription": "Peças artesanais feitas para estar ao seu lado e testemunhar os momentos significativos da vida.",
    "Shop.title": "Peças artesanais feitas para estar ao seu lado e testemunhar os momentos significativos da vida.",
    "AboutPage.metaTitle": "Sobre — HUMPBUCK Montres",
    "AboutPage.metaDescription": "Peças artesanais feitas para estar ao seu lado e testemunhar os momentos significativos da vida.",
    "BlogPage.metaDescription": "Peças artesanais feitas para estar ao seu lado e testemunhar os momentos significativos da vida.",
    "BlogPage.intro": "Peças artesanais feitas para estar ao seu lado e testemunhar os momentos significativos da vida.",
    "Home.recommendedIntro": "Peças artesanais feitas para estar ao seu lado e testemunhar os momentos significativos da vida.",
    "Home.newsletterTitle": "NOVOS LANÇAMENTOS DE RELÓGIOS",
    "BlogPage.metaTitle": "Blog — HUMPBUCK",
    "BlogPage.ogTitle": "Blog — HUMPBUCK",
    "BlogPage.kicker": "Diário",
    "BlogPage.title": "Blog"
  },
  "fr": {
    "SiteMetadata.titleDefault": "HUMPBUCK Montres - Cadeaux porteurs de temps et d'amour",
    "SiteMetadata.descriptionDefault": "Garde-temps artisanaux conçus pour rester à vos côtés et témoigner des moments significatifs de la vie.",
    "SiteMetadata.ogTitle": "HUMPBUCK Montres - Cadeaux porteurs de temps et d'amour",
    "SiteMetadata.ogDescription": "Garde-temps artisanaux conçus pour rester à vos côtés et témoigner des moments significatifs de la vie.",
    "Footer.tagline": "Garde-temps artisanaux conçus pour rester à vos côtés et témoigner des moments significatifs de la vie.",
    "Home.metaTitle": "HUMPBUCK Montres - Cadeaux porteurs de temps et d'amour",
    "Home.metaDescription": "Garde-temps artisanaux conçus pour rester à vos côtés et témoigner des moments significatifs de la vie.",
    "Home.ogTitle": "HUMPBUCK Montres - Cadeaux porteurs de temps et d'amour",
    "Home.ogDescription": "Garde-temps artisanaux conçus pour rester à vos côtés et témoigner des moments significatifs de la vie.",
    "Home.mechanicalHeroTitle": "HUMPBUCK Montres",
    "Home.mechanicalHeroLead": "Garde-temps artisanaux conçus pour rester à vos côtés et témoigner des moments significatifs de la vie.",
    "Home.mechanicalHeroBadge": "Cadeaux · Temps et amour",
    "Home.mechanicalHeroChipAutomatic": "Savoir-faire",
    "Home.mechanicalHeroChipSkeleton": "Étapes",
    "Home.mechanicalHeroChipFinishing": "Compagnie",
    "Home.newsletterBody": "Garde-temps artisanaux conçus pour rester à vos côtés et témoigner des moments significatifs de la vie.",
    "Shop.metaTitle": "Acheter des montres cadeaux porteuses de sens",
    "Shop.metaDescription": "Garde-temps artisanaux conçus pour rester à vos côtés et témoigner des moments significatifs de la vie.",
    "Shop.ogTitle": "Acheter des montres cadeaux porteuses de sens · HUMPBUCK",
    "Shop.ogDescription": "Garde-temps artisanaux conçus pour rester à vos côtés et témoigner des moments significatifs de la vie.",
    "Shop.title": "Garde-temps artisanaux conçus pour rester à vos côtés et témoigner des moments significatifs de la vie.",
    "AboutPage.metaTitle": "À propos — HUMPBUCK Montres",
    "AboutPage.metaDescription": "Garde-temps artisanaux conçus pour rester à vos côtés et témoigner des moments significatifs de la vie.",
    "BlogPage.metaDescription": "Garde-temps artisanaux conçus pour rester à vos côtés et témoigner des moments significatifs de la vie.",
    "BlogPage.intro": "Garde-temps artisanaux conçus pour rester à vos côtés et témoigner des moments significatifs de la vie.",
    "Home.recommendedIntro": "Garde-temps artisanaux conçus pour rester à vos côtés et témoigner des moments significatifs de la vie.",
    "Home.newsletterTitle": "NOUVELLES SORTIES DE MONTRES",
    "BlogPage.metaTitle": "Blog — HUMPBUCK",
    "BlogPage.ogTitle": "Blog — HUMPBUCK",
    "BlogPage.kicker": "Journal",
    "BlogPage.title": "Blog"
  },
  "it": {
    "SiteMetadata.titleDefault": "HUMPBUCK Montres - Regali di tempo e amore con significato",
    "SiteMetadata.descriptionDefault": "Segnatempo artigianali pensati per restare al tuo fianco e testimoniare i momenti significativi della vita.",
    "SiteMetadata.ogTitle": "HUMPBUCK Montres - Regali di tempo e amore con significato",
    "SiteMetadata.ogDescription": "Segnatempo artigianali pensati per restare al tuo fianco e testimoniare i momenti significativi della vita.",
    "Footer.tagline": "Segnatempo artigianali pensati per restare al tuo fianco e testimoniare i momenti significativi della vita.",
    "Home.metaTitle": "HUMPBUCK Montres - Regali di tempo e amore con significato",
    "Home.metaDescription": "Segnatempo artigianali pensati per restare al tuo fianco e testimoniare i momenti significativi della vita.",
    "Home.ogTitle": "HUMPBUCK Montres - Regali di tempo e amore con significato",
    "Home.ogDescription": "Segnatempo artigianali pensati per restare al tuo fianco e testimoniare i momenti significativi della vita.",
    "Home.mechanicalHeroTitle": "HUMPBUCK Montres",
    "Home.mechanicalHeroLead": "Segnatempo artigianali pensati per restare al tuo fianco e testimoniare i momenti significativi della vita.",
    "Home.mechanicalHeroBadge": "Regali · Tempo e amore",
    "Home.mechanicalHeroChipAutomatic": "Artigianalità",
    "Home.mechanicalHeroChipSkeleton": "Tappe",
    "Home.mechanicalHeroChipFinishing": "Compagnia",
    "Home.newsletterBody": "Segnatempo artigianali pensati per restare al tuo fianco e testimoniare i momenti significativi della vita.",
    "Shop.metaTitle": "Acquista orologi regalo con significato",
    "Shop.metaDescription": "Segnatempo artigianali pensati per restare al tuo fianco e testimoniare i momenti significativi della vita.",
    "Shop.ogTitle": "Acquista orologi regalo con significato · HUMPBUCK",
    "Shop.ogDescription": "Segnatempo artigianali pensati per restare al tuo fianco e testimoniare i momenti significativi della vita.",
    "Shop.title": "Segnatempo artigianali pensati per restare al tuo fianco e testimoniare i momenti significativi della vita.",
    "AboutPage.metaTitle": "Chi siamo — HUMPBUCK Montres",
    "AboutPage.metaDescription": "Segnatempo artigianali pensati per restare al tuo fianco e testimoniare i momenti significativi della vita.",
    "BlogPage.metaDescription": "Segnatempo artigianali pensati per restare al tuo fianco e testimoniare i momenti significativi della vita.",
    "BlogPage.intro": "Segnatempo artigianali pensati per restare al tuo fianco e testimoniare i momenti significativi della vita.",
    "Home.recommendedIntro": "Segnatempo artigianali pensati per restare al tuo fianco e testimoniare i momenti significativi della vita.",
    "Home.newsletterTitle": "NUOVI LANCI DI OROLOGI",
    "BlogPage.metaTitle": "Blog — HUMPBUCK",
    "BlogPage.ogTitle": "Blog — HUMPBUCK",
    "BlogPage.kicker": "Diario",
    "BlogPage.title": "Blog"
  },
  "nl": {
    "SiteMetadata.titleDefault": "HUMPBUCK Montres - Betekenisvolle geschenken van tijd en liefde",
    "SiteMetadata.descriptionDefault": "Handgemaakte timepieces ontworpen om aan je zijde te blijven en de betekenisvolle momenten in het leven mee te maken.",
    "SiteMetadata.ogTitle": "HUMPBUCK Montres - Betekenisvolle geschenken van tijd en liefde",
    "SiteMetadata.ogDescription": "Handgemaakte timepieces ontworpen om aan je zijde te blijven en de betekenisvolle momenten in het leven mee te maken.",
    "Footer.tagline": "Handgemaakte timepieces ontworpen om aan je zijde te blijven en de betekenisvolle momenten in het leven mee te maken.",
    "Home.metaTitle": "HUMPBUCK Montres - Betekenisvolle geschenken van tijd en liefde",
    "Home.metaDescription": "Handgemaakte timepieces ontworpen om aan je zijde te blijven en de betekenisvolle momenten in het leven mee te maken.",
    "Home.ogTitle": "HUMPBUCK Montres - Betekenisvolle geschenken van tijd en liefde",
    "Home.ogDescription": "Handgemaakte timepieces ontworpen om aan je zijde te blijven en de betekenisvolle momenten in het leven mee te maken.",
    "Home.mechanicalHeroTitle": "HUMPBUCK Montres",
    "Home.mechanicalHeroLead": "Handgemaakte timepieces ontworpen om aan je zijde te blijven en de betekenisvolle momenten in het leven mee te maken.",
    "Home.mechanicalHeroBadge": "Geschenken · Tijd en liefde",
    "Home.mechanicalHeroChipAutomatic": "Vakmanschap",
    "Home.mechanicalHeroChipSkeleton": "Mijlpalen",
    "Home.mechanicalHeroChipFinishing": "Gezelschap",
    "Home.newsletterBody": "Handgemaakte timepieces ontworpen om aan je zijde te blijven en de betekenisvolle momenten in het leven mee te maken.",
    "Shop.metaTitle": "Betekenisvolle cadeau-horloges shoppen",
    "Shop.metaDescription": "Handgemaakte timepieces ontworpen om aan je zijde te blijven en de betekenisvolle momenten in het leven mee te maken.",
    "Shop.ogTitle": "Betekenisvolle cadeau-horloges shoppen · HUMPBUCK",
    "Shop.ogDescription": "Handgemaakte timepieces ontworpen om aan je zijde te blijven en de betekenisvolle momenten in het leven mee te maken.",
    "Shop.title": "Handgemaakte timepieces ontworpen om aan je zijde te blijven en de betekenisvolle momenten in het leven mee te maken.",
    "AboutPage.metaTitle": "Over — HUMPBUCK Montres",
    "AboutPage.metaDescription": "Handgemaakte timepieces ontworpen om aan je zijde te blijven en de betekenisvolle momenten in het leven mee te maken.",
    "BlogPage.metaDescription": "Handgemaakte timepieces ontworpen om aan je zijde te blijven en de betekenisvolle momenten in het leven mee te maken.",
    "BlogPage.intro": "Handgemaakte timepieces ontworpen om aan je zijde te blijven en de betekenisvolle momenten in het leven mee te maken.",
    "Home.recommendedIntro": "Handgemaakte timepieces ontworpen om aan je zijde te blijven en de betekenisvolle momenten in het leven mee te maken.",
    "Home.newsletterTitle": "NIEUWE HORLOGE-RELEASES",
    "BlogPage.metaTitle": "Blog — HUMPBUCK",
    "BlogPage.ogTitle": "Blog — HUMPBUCK",
    "BlogPage.kicker": "Dagboek",
    "BlogPage.title": "Blog"
  },
  "hu": {
    "SiteMetadata.titleDefault": "HUMPBUCK Montres - Időt és szeretetet hordozó ajándékok",
    "SiteMetadata.descriptionDefault": "Kézműves órák, amelyek melletted maradnak és végigkísérik az élet értelmes pillanatait.",
    "SiteMetadata.ogTitle": "HUMPBUCK Montres - Időt és szeretetet hordozó ajándékok",
    "SiteMetadata.ogDescription": "Kézműves órák, amelyek melletted maradnak és végigkísérik az élet értelmes pillanatait.",
    "Footer.tagline": "Kézműves órák, amelyek melletted maradnak és végigkísérik az élet értelmes pillanatait.",
    "Home.metaTitle": "HUMPBUCK Montres - Időt és szeretetet hordozó ajándékok",
    "Home.metaDescription": "Kézműves órák, amelyek melletted maradnak és végigkísérik az élet értelmes pillanatait.",
    "Home.ogTitle": "HUMPBUCK Montres - Időt és szeretetet hordozó ajándékok",
    "Home.ogDescription": "Kézműves órák, amelyek melletted maradnak és végigkísérik az élet értelmes pillanatait.",
    "Home.mechanicalHeroTitle": "HUMPBUCK Montres",
    "Home.mechanicalHeroLead": "Kézműves órák, amelyek melletted maradnak és végigkísérik az élet értelmes pillanatait.",
    "Home.mechanicalHeroBadge": "Ajándékok · Idő és szeretet",
    "Home.mechanicalHeroChipAutomatic": "Kézművesség",
    "Home.mechanicalHeroChipSkeleton": "Mérföldkövek",
    "Home.mechanicalHeroChipFinishing": "Társaság",
    "Home.newsletterBody": "Kézműves órák, amelyek melletted maradnak és végigkísérik az élet értelmes pillanatait.",
    "Shop.metaTitle": "Értelmes ajándékórák vásárlása",
    "Shop.metaDescription": "Kézműves órák, amelyek melletted maradnak és végigkísérik az élet értelmes pillanatait.",
    "Shop.ogTitle": "Értelmes ajándékórák vásárlása · HUMPBUCK",
    "Shop.ogDescription": "Kézműves órák, amelyek melletted maradnak és végigkísérik az élet értelmes pillanatait.",
    "Shop.title": "Kézműves órák, amelyek melletted maradnak és végigkísérik az élet értelmes pillanatait.",
    "AboutPage.metaTitle": "Rólunk — HUMPBUCK Montres",
    "AboutPage.metaDescription": "Kézműves órák, amelyek melletted maradnak és végigkísérik az élet értelmes pillanatait.",
    "BlogPage.metaDescription": "Kézműves órák, amelyek melletted maradnak és végigkísérik az élet értelmes pillanatait.",
    "BlogPage.intro": "Kézműves órák, amelyek melletted maradnak és végigkísérik az élet értelmes pillanatait.",
    "Home.recommendedIntro": "Kézműves órák, amelyek melletted maradnak és végigkísérik az élet értelmes pillanatait.",
    "Home.newsletterTitle": "ÚJ ÓRA MEGJELENÉSEK",
    "BlogPage.metaTitle": "Blog — HUMPBUCK",
    "BlogPage.ogTitle": "Blog — HUMPBUCK",
    "BlogPage.kicker": "Napló",
    "BlogPage.title": "Blog"
  },
  "ko": {
    "SiteMetadata.titleDefault": "HUMPBUCK Montres - 시간과 사랑을 담은 의미 있는 선물",
    "SiteMetadata.descriptionDefault": "곁에 머무르며 인생의 의미 있는 순간을 함께하는 수공예 타임피스.",
    "SiteMetadata.ogTitle": "HUMPBUCK Montres - 시간과 사랑을 담은 의미 있는 선물",
    "SiteMetadata.ogDescription": "곁에 머무르며 인생의 의미 있는 순간을 함께하는 수공예 타임피스.",
    "Footer.tagline": "곁에 머무르며 인생의 의미 있는 순간을 함께하는 수공예 타임피스.",
    "Home.metaTitle": "HUMPBUCK Montres - 시간과 사랑을 담은 의미 있는 선물",
    "Home.metaDescription": "곁에 머무르며 인생의 의미 있는 순간을 함께하는 수공예 타임피스.",
    "Home.ogTitle": "HUMPBUCK Montres - 시간과 사랑을 담은 의미 있는 선물",
    "Home.ogDescription": "곁에 머무르며 인생의 의미 있는 순간을 함께하는 수공예 타임피스.",
    "Home.mechanicalHeroTitle": "HUMPBUCK Montres",
    "Home.mechanicalHeroLead": "곁에 머무르며 인생의 의미 있는 순간을 함께하는 수공예 타임피스.",
    "Home.mechanicalHeroBadge": "선물 · 시간과 사랑",
    "Home.mechanicalHeroChipAutomatic": "장인 정신",
    "Home.mechanicalHeroChipSkeleton": "이정표",
    "Home.mechanicalHeroChipFinishing": "동행",
    "Home.newsletterBody": "곁에 머무르며 인생의 의미 있는 순간을 함께하는 수공예 타임피스.",
    "Shop.metaTitle": "의미 있는 선물 시계 쇼핑",
    "Shop.metaDescription": "곁에 머무르며 인생의 의미 있는 순간을 함께하는 수공예 타임피스.",
    "Shop.ogTitle": "의미 있는 선물 시계 쇼핑 · HUMPBUCK",
    "Shop.ogDescription": "곁에 머무르며 인생의 의미 있는 순간을 함께하는 수공예 타임피스.",
    "Shop.title": "곁에 머무르며 인생의 의미 있는 순간을 함께하는 수공예 타임피스.",
    "AboutPage.metaTitle": "소개 — HUMPBUCK Montres",
    "AboutPage.metaDescription": "곁에 머무르며 인생의 의미 있는 순간을 함께하는 수공예 타임피스.",
    "BlogPage.metaDescription": "곁에 머무르며 인생의 의미 있는 순간을 함께하는 수공예 타임피스.",
    "BlogPage.intro": "곁에 머무르며 인생의 의미 있는 순간을 함께하는 수공예 타임피스.",
    "Home.recommendedIntro": "곁에 머무르며 인생의 의미 있는 순간을 함께하는 수공예 타임피스.",
    "Home.newsletterTitle": "신규 시계 출시",
    "BlogPage.metaTitle": "블로그 — HUMPBUCK",
    "BlogPage.ogTitle": "블로그 — HUMPBUCK",
    "BlogPage.kicker": "저널",
    "BlogPage.title": "블로그"
  },
  "ja": {
    "SiteMetadata.titleDefault": "HUMPBUCK Montres - 時間と愛を贈る意味あるギフト",
    "SiteMetadata.descriptionDefault": "そばに寄り添い、人生の大切な瞬間を共に見届けるハンドクラフトタイムピース。",
    "SiteMetadata.ogTitle": "HUMPBUCK Montres - 時間と愛を贈る意味あるギフト",
    "SiteMetadata.ogDescription": "そばに寄り添い、人生の大切な瞬間を共に見届けるハンドクラフトタイムピース。",
    "Footer.tagline": "そばに寄り添い、人生の大切な瞬間を共に見届けるハンドクラフトタイムピース。",
    "Home.metaTitle": "HUMPBUCK Montres - 時間と愛を贈る意味あるギフト",
    "Home.metaDescription": "そばに寄り添い、人生の大切な瞬間を共に見届けるハンドクラフトタイムピース。",
    "Home.ogTitle": "HUMPBUCK Montres - 時間と愛を贈る意味あるギフト",
    "Home.ogDescription": "そばに寄り添い、人生の大切な瞬間を共に見届けるハンドクラフトタイムピース。",
    "Home.mechanicalHeroTitle": "HUMPBUCK Montres",
    "Home.mechanicalHeroLead": "そばに寄り添い、人生の大切な瞬間を共に見届けるハンドクラフトタイムピース。",
    "Home.mechanicalHeroBadge": "ギフト · 時間と愛",
    "Home.mechanicalHeroChipAutomatic": "クラフトマンシップ",
    "Home.mechanicalHeroChipSkeleton": "マイルストーン",
    "Home.mechanicalHeroChipFinishing": "寄り添い",
    "Home.newsletterBody": "そばに寄り添い、人生の大切な瞬間を共に見届けるハンドクラフトタイムピース。",
    "Shop.metaTitle": "意味あるギフトウォッチをショップ",
    "Shop.metaDescription": "そばに寄り添い、人生の大切な瞬間を共に見届けるハンドクラフトタイムピース。",
    "Shop.ogTitle": "意味あるギフトウォッチ · HUMPBUCK",
    "Shop.ogDescription": "そばに寄り添い、人生の大切な瞬間を共に見届けるハンドクラフトタイムピース。",
    "Shop.title": "そばに寄り添い、人生の大切な瞬間を共に見届けるハンドクラフトタイムピース。",
    "AboutPage.metaTitle": "About — HUMPBUCK Montres",
    "AboutPage.metaDescription": "そばに寄り添い、人生の大切な瞬間を共に見届けるハンドクラフトタイムピース。",
    "BlogPage.metaDescription": "そばに寄り添い、人生の大切な瞬間を共に見届けるハンドクラフトタイムピース。",
    "BlogPage.intro": "そばに寄り添い、人生の大切な瞬間を共に見届けるハンドクラフトタイムピース。",
    "Home.recommendedIntro": "そばに寄り添い、人生の大切な瞬間を共に見届けるハンドクラフトタイムピース。",
    "Home.newsletterTitle": "新作ウォッチ入荷",
    "BlogPage.metaTitle": "ブログ — HUMPBUCK",
    "BlogPage.ogTitle": "ブログ — HUMPBUCK",
    "BlogPage.kicker": "ジャーナル",
    "BlogPage.title": "ブログ"
  },
  "ru": {
    "SiteMetadata.titleDefault": "HUMPBUCK Montres - Значимые подарки времени и любви",
    "SiteMetadata.descriptionDefault": "Часы ручной работы, созданные быть рядом с вами и свидетельствовать значимые моменты жизни.",
    "SiteMetadata.ogTitle": "HUMPBUCK Montres - Значимые подарки времени и любви",
    "SiteMetadata.ogDescription": "Часы ручной работы, созданные быть рядом с вами и свидетельствовать значимые моменты жизни.",
    "Footer.tagline": "Часы ручной работы, созданные быть рядом с вами и свидетельствовать значимые моменты жизни.",
    "Home.metaTitle": "HUMPBUCK Montres - Значимые подарки времени и любви",
    "Home.metaDescription": "Часы ручной работы, созданные быть рядом с вами и свидетельствовать значимые моменты жизни.",
    "Home.ogTitle": "HUMPBUCK Montres - Значимые подарки времени и любви",
    "Home.ogDescription": "Часы ручной работы, созданные быть рядом с вами и свидетельствовать значимые моменты жизни.",
    "Home.mechanicalHeroTitle": "HUMPBUCK Montres",
    "Home.mechanicalHeroLead": "Часы ручной работы, созданные быть рядом с вами и свидетельствовать значимые моменты жизни.",
    "Home.mechanicalHeroBadge": "Подарки · Время и любовь",
    "Home.mechanicalHeroChipAutomatic": "Мастерство",
    "Home.mechanicalHeroChipSkeleton": "Вехи",
    "Home.mechanicalHeroChipFinishing": "Товарищество",
    "Home.newsletterBody": "Часы ручной работы, созданные быть рядом с вами и свидетельствовать значимые моменты жизни.",
    "Shop.metaTitle": "Купить часы как значимый подарок",
    "Shop.metaDescription": "Часы ручной работы, созданные быть рядом с вами и свидетельствовать значимые моменты жизни.",
    "Shop.ogTitle": "Купить часы как значимый подарок · HUMPBUCK",
    "Shop.ogDescription": "Часы ручной работы, созданные быть рядом с вами и свидетельствовать значимые моменты жизни.",
    "Shop.title": "Часы ручной работы, созданные быть рядом с вами и свидетельствовать значимые моменты жизни.",
    "AboutPage.metaTitle": "О нас — HUMPBUCK Montres",
    "AboutPage.metaDescription": "Часы ручной работы, созданные быть рядом с вами и свидетельствовать значимые моменты жизни.",
    "BlogPage.metaDescription": "Часы ручной работы, созданные быть рядом с вами и свидетельствовать значимые моменты жизни.",
    "BlogPage.intro": "Часы ручной работы, созданные быть рядом с вами и свидетельствовать значимые моменты жизни.",
    "Home.recommendedIntro": "Часы ручной работы, созданные быть рядом с вами и свидетельствовать значимые моменты жизни.",
    "Home.newsletterTitle": "НОВЫЕ ПОСТУПЛЕНИЯ ЧАСОВ",
    "BlogPage.metaTitle": "Блог — HUMPBUCK",
    "BlogPage.ogTitle": "Блог — HUMPBUCK",
    "BlogPage.kicker": "Журнал",
    "BlogPage.title": "Блог"
  },
  "he": {
    "SiteMetadata.titleDefault": "HUMPBUCK Montres - מתנות משמעותיות של זמן ואהבה",
    "SiteMetadata.descriptionDefault": "שעוני יוקרה מעשה יד שנוצרו להישאר לצידכם ולהיות עדים לרגעים המשמעותיים בחיים.",
    "SiteMetadata.ogTitle": "HUMPBUCK Montres - מתנות משמעותיות של זמן ואהבה",
    "SiteMetadata.ogDescription": "שעוני יוקרה מעשה יד שנוצרו להישאר לצידכם ולהיות עדים לרגעים המשמעותיים בחיים.",
    "Footer.tagline": "שעוני יוקרה מעשה יד שנוצרו להישאר לצידכם ולהיות עדים לרגעים המשמעותיים בחיים.",
    "Home.metaTitle": "HUMPBUCK Montres - מתנות משמעותיות של זמן ואהבה",
    "Home.metaDescription": "שעוני יוקרה מעשה יד שנוצרו להישאר לצידכם ולהיות עדים לרגעים המשמעותיים בחיים.",
    "Home.ogTitle": "HUMPBUCK Montres - מתנות משמעותיות של זמן ואהבה",
    "Home.ogDescription": "שעוני יוקרה מעשה יד שנוצרו להישאר לצידכם ולהיות עדים לרגעים המשמעותיים בחיים.",
    "Home.mechanicalHeroTitle": "HUMPBUCK Montres",
    "Home.mechanicalHeroLead": "שעוני יוקרה מעשה יד שנוצרו להישאר לצידכם ולהיות עדים לרגעים המשמעותיים בחיים.",
    "Home.mechanicalHeroBadge": "מתנות · זמן ואהבה",
    "Home.mechanicalHeroChipAutomatic": "אומנות",
    "Home.mechanicalHeroChipSkeleton": "אבני דרך",
    "Home.mechanicalHeroChipFinishing": "ליווי",
    "Home.newsletterBody": "שעוני יוקרה מעשה יד שנוצרו להישאר לצידכם ולהיות עדים לרגעים המשמעותיים בחיים.",
    "Shop.metaTitle": "קניית שעוני מתנה משמעותיים",
    "Shop.metaDescription": "שעוני יוקרה מעשה יד שנוצרו להישאר לצידכם ולהיות עדים לרגעים המשמעותיים בחיים.",
    "Shop.ogTitle": "קניית שעוני מתנה משמעותיים · HUMPBUCK",
    "Shop.ogDescription": "שעוני יוקרה מעשה יד שנוצרו להישאר לצידכם ולהיות עדים לרגעים המשמעותיים בחיים.",
    "Shop.title": "שעוני יוקרה מעשה יד שנוצרו להישאר לצידכם ולהיות עדים לרגעים המשמעותיים בחיים.",
    "AboutPage.metaTitle": "אודות — HUMPBUCK Montres",
    "AboutPage.metaDescription": "שעוני יוקרה מעשה יד שנוצרו להישאר לצידכם ולהיות עדים לרגעים המשמעותיים בחיים.",
    "BlogPage.metaDescription": "שעוני יוקרה מעשה יד שנוצרו להישאר לצידכם ולהיות עדים לרגעים המשמעותיים בחיים.",
    "BlogPage.intro": "שעוני יוקרה מעשה יד שנוצרו להישאר לצידכם ולהיות עדים לרגעים המשמעותיים בחיים.",
    "Home.recommendedIntro": "שעוני יוקרה מעשה יד שנוצרו להישאר לצידכם ולהיות עדים לרגעים המשמעותיים בחיים.",
    "Home.newsletterTitle": "השקות שעונים חדשות",
    "BlogPage.metaTitle": "בלוג — HUMPBUCK",
    "BlogPage.ogTitle": "בלוג — HUMPBUCK",
    "BlogPage.kicker": "יומן",
    "BlogPage.title": "בלוג"
  },
  "ar": {
    "SiteMetadata.titleDefault": "HUMPBUCK Montres - هدايا ذات معنى للوقت والحب",
    "SiteMetadata.descriptionDefault": "ساعات مصنوعة يدويًا مصممة لتبقى إلى جانبك وتشهد اللحظات المعنوية في الحياة.",
    "SiteMetadata.ogTitle": "HUMPBUCK Montres - هدايا ذات معنى للوقت والحب",
    "SiteMetadata.ogDescription": "ساعات مصنوعة يدويًا مصممة لتبقى إلى جانبك وتشهد اللحظات المعنوية في الحياة.",
    "Footer.tagline": "ساعات مصنوعة يدويًا مصممة لتبقى إلى جانبك وتشهد اللحظات المعنوية في الحياة.",
    "Home.metaTitle": "HUMPBUCK Montres - هدايا ذات معنى للوقت والحب",
    "Home.metaDescription": "ساعات مصنوعة يدويًا مصممة لتبقى إلى جانبك وتشهد اللحظات المعنوية في الحياة.",
    "Home.ogTitle": "HUMPBUCK Montres - هدايا ذات معنى للوقت والحب",
    "Home.ogDescription": "ساعات مصنوعة يدويًا مصممة لتبقى إلى جانبك وتشهد اللحظات المعنوية في الحياة.",
    "Home.mechanicalHeroTitle": "HUMPBUCK Montres",
    "Home.mechanicalHeroLead": "ساعات مصنوعة يدويًا مصممة لتبقى إلى جانبك وتشهد اللحظات المعنوية في الحياة.",
    "Home.mechanicalHeroBadge": "هدايا · الوقت والحب",
    "Home.mechanicalHeroChipAutomatic": "حرفية",
    "Home.mechanicalHeroChipSkeleton": "محطات",
    "Home.mechanicalHeroChipFinishing": "رفقة",
    "Home.newsletterBody": "ساعات مصنوعة يدويًا مصممة لتبقى إلى جانبك وتشهد اللحظات المعنوية في الحياة.",
    "Shop.metaTitle": "تسوق ساعات هدايا ذات معنى",
    "Shop.metaDescription": "ساعات مصنوعة يدويًا مصممة لتبقى إلى جانبك وتشهد اللحظات المعنوية في الحياة.",
    "Shop.ogTitle": "تسوق ساعات هدايا ذات معنى · HUMPBUCK",
    "Shop.ogDescription": "ساعات مصنوعة يدويًا مصممة لتبقى إلى جانبك وتشهد اللحظات المعنوية في الحياة.",
    "Shop.title": "ساعات مصنوعة يدويًا مصممة لتبقى إلى جانبك وتشهد اللحظات المعنوية في الحياة.",
    "AboutPage.metaTitle": "من نحن — HUMPBUCK Montres",
    "AboutPage.metaDescription": "ساعات مصنوعة يدويًا مصممة لتبقى إلى جانبك وتشهد اللحظات المعنوية في الحياة.",
    "BlogPage.metaDescription": "ساعات مصنوعة يدويًا مصممة لتبقى إلى جانبك وتشهد اللحظات المعنوية في الحياة.",
    "BlogPage.intro": "ساعات مصنوعة يدويًا مصممة لتبقى إلى جانبك وتشهد اللحظات المعنوية في الحياة.",
    "Home.recommendedIntro": "ساعات مصنوعة يدويًا مصممة لتبقى إلى جانبك وتشهد اللحظات المعنوية في الحياة.",
    "Home.newsletterTitle": "إصدارات ساعات جديدة",
    "BlogPage.metaTitle": "المدونة — HUMPBUCK",
    "BlogPage.ogTitle": "المدونة — HUMPBUCK",
    "BlogPage.kicker": "المجلة",
    "BlogPage.title": "المدونة"
  }
}\n